glob_tries/__init__.py
glob_tries/py.typed
glob_tries-1.0.2.dist-info/LICENSE
glob_tries-1.0.2.dist-info/METADATA
glob_tries-1.0.2.dist-info/WHEEL
glob_tries-1.0.2.dist-info/RECORD
