Metadata-Version: 2.1
Name: glob-tries
Version: 1.0.2
Summary: Utilities for efficient glob matching using tries
Home-page: https://github.com/arcesium/glob-tries
License: BSD-3-Clause
Author: Zack Robinson
Author-email: zachary.robinson@arcesium.com
Requires-Python: >=3.9,<4.0
Classifier: License :: OSI Approved :: BSD License
Classifier: Programming Language :: Python :: 3
Classifier: Programming Language :: Python :: 3.9
Classifier: Programming Language :: Python :: 3.10
Classifier: Programming Language :: Python :: 3.11
Project-URL: Repository, https://github.com/arcesium/glob-tries
